{
  "id": "929888",
  "title": "보스턴다이나믹스의 로봇이 왜 한국 로봇이야?",
  "category": "",
  "author": "ㅇㅇ",
  "date": "2026.01.10 05:55:11",
  "views": 0,
  "likes": 0,
  "comments": 0,
  "content": "\n\t\t\t\t\t\t\t<p><br></p><p style=\"margin:0px;padding:0px;border:0px;vertical-align:baseline;background:transparent;font-style:normal;\">우리는 제조 담당이고 ㅋ</p><p style=\"margin:0px;padding:0px;border:0px;vertical-align:baseline;background:transparent;font-style:normal;\"><br></p><p style=\"margin:0px;padding:0px;border:0px;vertical-align:baseline;background:transparent;font-style:normal;\">소프트웨어는 어차피 못만들잖아</p><p style=\"margin:0px;padding:0px;border:0px;vertical-align:baseline;background:transparent;font-style:normal;\"><br></p><p style=\"margin:0px;padding:0px;border:0px;vertical-align:baseline;background:transparent;font-style:normal;\">앙꼬없는 찐빵인데 왜 자꾸 한국로봇이야</p><p style=\"margin:0px;padding:0px;border:0px;vertical-align:baseline;background:transparent;font-style:normal;\"><br></p><p style=\"margin:0px;padding:0px;border:0px;vertical-align:baseline;background:transparent;font-style:normal;\">우리는 그냥 대신 만들어주는 노예아님?&nbsp;</p><p style=\"margin:0px;padding:0px;border:0px;vertical-align:baseline;background:transparent;font-style:normal;\"><br></p><p style=\"margin:0px;padding:0px;border:0px;vertical-align:baseline;background:transparent;font-style:normal;\">유튜버 병신새끼들 국뽕 존나넣네&nbsp;</p><p style=\"margin:0px;padding:0px;border:0px;vertical-align:baseline;background:transparent;font-style:normal;\"><br></p><p style=\"margin:0px;padding:0px;border:0px;vertical-align:baseline;background:transparent;font-style:normal;\">우리나라 실무진이 제조말고 핵심 기술로 못만들어&nbsp;</p><p style=\"margin:0px;padding:0px;border:0px;vertical-align:baseline;background:transparent;font-style:normal;\"><br style=\"color:rgb(204,204,204);font-family:'맑은 고딕';font-size:12px;font-style:normal;font-weight:400;letter-spacing:normal;text-indent:0px;text-transform:none;word-spacing:0px;white-space:normal;background-color:rgb(25,25,25);\">그것이 균형이고 조선인을 다루는 글로벌리스트들의 습법이야</p><p style=\"margin:0px;padding:0px;border:0px;vertical-align:baseline;background:transparent;font-style:normal;\"><br></p>\t\t\t\t\t\t\t\n\t\t\t\t\t\t\t",
  "contentText": "우리는 제조 담당이고 ㅋ소프트웨어는 어차피 못만들잖아앙꼬없는 찐빵인데 왜 자꾸 한국로봇이야우리는 그냥 대신 만들어주는 노예아님? 유튜버 병신새끼들 국뽕 존나넣네 우리나라 실무진이 제조말고 핵심 기술로 못만들어 그것이 균형이고 조선인을 다루는 글로벌리스트들의 습법이야",
  "images": [],
  "url": "https://gall.dcinside.com/mgallery/board/view/?id=thesingularity&no=929888",
  "crawledAt": "2026-01-09T21:35:24.165Z"
}