{
  "id": "wired-ai-5qnnkva",
  "sourceId": "wired-ai",
  "sourceName": "Wired AI",
  "sourceTier": "A",
  "sourceType": "news",
  "title": "Google Is Adding an ‘AI Inbox’ to Gmail That Summarizes Emails",
  "link": "https://www.wired.com/story/google-ai-inbox-gmail/",
  "pubDate": "Thu, 08 Jan 2026 13:00:00 +0000",
  "contentSnippet": "New Gmail features, powered by the Gemini model, are part of Google’s continued push for users to incorporate AI into their daily life and conversations.",
  "content": "New Gmail features, powered by the Gemini model, are part of Google’s continued push for users to incorporate AI into their daily life and conversations.",
  "categories": [
    "Gear",
    "Gear / Gear News and Events"
  ],
  "fetchedAt": "2026-01-14T01:48:42.010Z"
}